<?xml version = '1.0' encoding = 'UTF-8'?>
<Relation class="oracle.dbtools.crest.model.design.logical.Relation" name="Relation_29" id="DC24A8E7-01F3-DF50-B2C9-5976102EDBAD" directorySegmentName="seg_0">
   <createdBy>Evan</createdBy>
   <createdTime>2011-12-11 21:32:14 UTC</createdTime>
   <ownerDesignName>Project ERD</ownerDesignName>
   <identifying>true</identifying>
   <nameOnSource>have</nameOnSource>
   <nameOnTarget>be at</nameOnTarget>
   <optionalSource>true</optionalSource>
   <optionalTarget>false</optionalTarget>
   <sourceCardinality>1</sourceCardinality>
   <sourceEntity>C48BA620-5E56-0043-441A-8C5D2CB00B8E</sourceEntity>
   <targetCardinalityString>*</targetCardinalityString>
   <targetEntity>2E6941AD-277F-1863-CE2C-061A53D60D06</targetEntity>
   <transferable>true</transferable>
</Relation>