<?xml version = '1.0' encoding = 'UTF-8'?>
<Relation class="oracle.dbtools.crest.model.design.logical.Relation" name="Relation_35" id="6352A186-B335-F48F-8D36-34812EB7B522" directorySegmentName="seg_0">
   <createdBy>Evan</createdBy>
   <createdTime>2011-12-12 20:07:06 UTC</createdTime>
   <ownerDesignName>Project ERD</ownerDesignName>
   <arc>A656A30E-162F-6143-EB8C-07EC10C6DED5</arc>
   <identifying>false</identifying>
   <nameOnSource>have</nameOnSource>
   <nameOnTarget>be for</nameOnTarget>
   <optionalSource>false</optionalSource>
   <optionalTarget>true</optionalTarget>
   <sourceCardinality>1</sourceCardinality>
   <sourceEntity>115C9C64-D963-73FF-D4E0-771EC069F77A</sourceEntity>
   <targetCardinalityString>*</targetCardinalityString>
   <targetEntity>50F88D8F-0795-4929-F407-DE36C1E0D84A</targetEntity>
   <transferable>true</transferable>
</Relation>